mylib_014/__init__.py
mylib_014-0.1.dist-info/LICENSE.txt
mylib_014-0.1.dist-info/METADATA
mylib_014-0.1.dist-info/WHEEL
mylib_014-0.1.dist-info/top_level.txt
mylib_014-0.1.dist-info/RECORD
