Metadata-Version: 2.1
Name: mylib-014
Version: 0.1
Summary: for calculating square
Author: Diksha
Author-email: Dikshaparwekar@gmail.com
Classifier: Programming Language :: Python :: 3
Classifier: License :: OSI Approved :: MIT License
Classifier: Operating System :: OS Independent
License-File: LICENSE.txt
